hanzo_agents/__init__.py
hanzo_agents/cli.py
hanzo_agents-0.1.2.dist-info/METADATA
hanzo_agents-0.1.2.dist-info/WHEEL
hanzo_agents-0.1.2.dist-info/entry_points.txt
hanzo_agents-0.1.2.dist-info/RECORD
