Metadata-Version: 2.4
Name: hanzo-agents
Version: 0.1.2
Summary: Multi-agent orchestration CLI for Hanzo AI
Project-URL: Homepage, https://hanzo.ai
Project-URL: Repository, https://github.com/hanzoai/python-sdk
Project-URL: Documentation, https://docs.hanzo.ai
Author-email: Hanzo AI <dev@hanzo.ai>
License: Apache-2.0
Keywords: agents,ai,cli,hanzo,orchestration
Classifier: Development Status :: 4 - Beta
Classifier: Intended Audience :: Developers
Classifier: License :: OSI Approved :: Apache Software License
Classifier: Programming Language :: Python :: 3
Classifier: Programming Language :: Python :: 3.10
Classifier: Programming Language :: Python :: 3.11
Classifier: Programming Language :: Python :: 3.12
Requires-Python: >=3.10
Requires-Dist: click>=8.0
Requires-Dist: hanzo-tools-agent>=0.2.0
Requires-Dist: rich>=13.0
Provides-Extra: dev
Requires-Dist: pytest; extra == 'dev'
Requires-Dist: ruff; extra == 'dev'
